richie_openedx_sync/__init__.py
richie_openedx_sync/apps.py
richie_openedx_sync/settings.py
richie_openedx_sync/signals.py
richie_openedx_sync/tasks.py
richie_openedx_sync/management/__init__.py
richie_openedx_sync/management/commands/__init__.py
richie_openedx_sync/management/commands/sync_courses_to_richie.py
richie_openedx_sync-1.4.0.dist-info/LICENSE
richie_openedx_sync-1.4.0.dist-info/METADATA
richie_openedx_sync-1.4.0.dist-info/WHEEL
richie_openedx_sync-1.4.0.dist-info/entry_points.txt
richie_openedx_sync-1.4.0.dist-info/top_level.txt
richie_openedx_sync-1.4.0.dist-info/RECORD
