Metadata-Version: 2.1
Name: richie-openedx-sync
Version: 1.4.0
Summary: Richie Open edX Synchronization application
Home-page: https://github.com/fccn/richie-openedx-sync
Author: FCT|FCCN NAU
Author-email: info@nau.edu.pt
License: AGPL 3.0
Keywords: Django,Open edX,MOOC,Richie
Platform: any
Classifier: Development Status :: 3 - Alpha
Classifier: Framework :: Django
Classifier: Framework :: Django :: 2.2
Classifier: License :: OSI Approved :: GNU Affero General Public License v3 or later (AGPLv3+)
Classifier: Programming Language :: Python :: 3
Classifier: Programming Language :: Python :: 3.5
Requires-Python: >=3.5
License-File: LICENSE
